birthday/__init__.py
birthday/fields.py
birthday/managers.py
birthday/models.py
birthday/tests/__init__.py
birthday/tests/conftest.py
birthday/tests/models.py
birthday/tests/settings.py
birthday/tests/test_models.py
django_birthday-0.1.4.dist-info/AUTHORS
django_birthday-0.1.4.dist-info/LICENSE
django_birthday-0.1.4.dist-info/METADATA
django_birthday-0.1.4.dist-info/WHEEL
django_birthday-0.1.4.dist-info/top_level.txt
django_birthday-0.1.4.dist-info/RECORD
